arch_github_package/__init__.py
arch_github_package/gh.py
arch_github_package/main.py
arch_github_package/pm.py
arch_github_package/state.py
arch_github_package-0.0.7.dist-info/METADATA
arch_github_package-0.0.7.dist-info/WHEEL
arch_github_package-0.0.7.dist-info/entry_points.txt
arch_github_package-0.0.7.dist-info/licenses/LICENSE
arch_github_package-0.0.7.dist-info/RECORD
