Metadata-Version: 2.1
Name: arch-github-package
Version: 0.0.7
Summary: Convert GitHub project releases to Archlinux package, with autoupdate.
Project-URL: Repository, https://github.com/jinliu/arch-github-package
Project-URL: Bug Tracker, https://github.com/jinliu/arch-github-package/issues
Author-email: Jin Liu <m.liu.jin@gmail.com>
License-File: LICENSE
Keywords: AUR,arch,archlinux,github,package,package-manager
Classifier: Development Status :: 2 - Pre-Alpha
Classifier: Environment :: Console
Classifier: License :: OSI Approved :: Apache Software License
Classifier: Operating System :: POSIX :: Linux
Classifier: Programming Language :: Python :: 3
Classifier: Topic :: System
Requires-Python: >=3.7
Requires-Dist: pygithub==1.58.*
Requires-Dist: tabulate==0.9.*
Requires-Dist: typer==0.9.*
